applications_download/__init__.py
applications_download/applications-schema.json
applications_download/applications.yaml
applications_download/applications_definition.py
applications_download/cli.py
applications_download/py.typed
applications_download/versions.yaml
applications_download-1.4.0.dist-info/LICENSE
applications_download-1.4.0.dist-info/METADATA
applications_download-1.4.0.dist-info/WHEEL
applications_download-1.4.0.dist-info/entry_points.txt
applications_download-1.4.0.dist-info/RECORD
