Metadata-Version: 2.3
Name: applications-download
Version: 1.4.0
Summary: Tools used to publish Python packages, Docker images and Helm charts for GitHub tag and branch
License: FreeBSD
Keywords: ci
Author: Camptocamp
Author-email: info@camptocamp.com
Requires-Python: >=3.10
Classifier: Development Status :: 5 - Production/Stable
Classifier: Environment :: Console
Classifier: Intended Audience :: Developers
Classifier: License :: OSI Approved :: MIT License
Classifier: Operating System :: OS Independent
Classifier: Programming Language :: Python
Classifier: Programming Language :: Python :: 3
Classifier: Programming Language :: Python :: 3.10
Classifier: Programming Language :: Python :: 3.11
Classifier: Programming Language :: Python :: 3.12
Classifier: Programming Language :: Python :: 3.13
Classifier: Typing :: Typed
Requires-Dist: PyYAML (>=6,<7)
Requires-Dist: jsonschema-validator-new (>=0,<1)
Requires-Dist: requests (>=2,<3)
Requires-Dist: ruamel.yaml (>=0,<1)
Project-URL: Bug Tracker, https://github.com/camptocamp/applications-download/issues
Project-URL: Repository, https://github.com/camptocamp/applications-download
